erever/__init__.py
erever/__main__.py
erever/assemble.py
erever/cbor.py
erever/colors.py
erever/context.py
erever/disassemble.py
erever/disassemble_mermaid.py
erever/disassemble_symbolic.py
erever/find_gadgets.py
erever/gas.py
erever/memory.py
erever/node.py
erever/opcodes.py
erever/precompiled_contracts.py
erever/secp256k1.py
erever/stack.py
erever/storage.py
erever/symbolic_stack.py
erever/types.py
erever/utils.py
erever-0.1.0.dist-info/METADATA
erever-0.1.0.dist-info/WHEEL
erever-0.1.0.dist-info/entry_points.txt
erever-0.1.0.dist-info/licenses/LICENSE
erever-0.1.0.dist-info/RECORD
