Metadata-Version: 2.3
Name: erever
Version: 0.1.0
Summary: A CLI tool for reversing EVM bytecodes, optimized for solving CTF challenges. Currently experimental and developed for personal use.
Author-email: minaminao <minaminaoy@gmail.com>
License-Expression: Apache-2.0
License-File: LICENSE
Requires-Python: >=3.12
Requires-Dist: aiohttp>=3.9.1
Requires-Dist: base58>=2.1.1
Requires-Dist: cbor2>=5.5.1
Requires-Dist: pycryptodome>=3.20.0
Requires-Dist: rlp>=3.0.0
Requires-Dist: setuptools>=74.1.2
Requires-Dist: web3>=7.2.0
